indipyclient/__init__.py
indipyclient/events.py
indipyclient/ipyclient.py
indipyclient/propertymembers.py
indipyclient/propertyvectors.py
indipyclient/queclient.py
indipyclient-0.9.0.dist-info/licenses/LICENSE
indipyclient-0.9.0.dist-info/WHEEL
indipyclient-0.9.0.dist-info/METADATA
indipyclient-0.9.0.dist-info/RECORD
