Metadata-Version: 2.4
Name: indipyclient
Version: 0.9.0
Summary: Pure python package, providing a set of classes which can be used to create scripts or clients to control remote instruments using the INDI protocol.
Keywords: indi,client,astronomy,instrument
Author-email: Bernard Czenkusz <bernie@skipole.co.uk>
Requires-Python: >=3.10
Classifier: License :: OSI Approved :: MIT License
Classifier: Operating System :: POSIX :: Linux
Classifier: Topic :: Scientific/Engineering :: Astronomy
Classifier: Topic :: Scientific/Engineering :: Interface Engine/Protocol Translator
License-File: LICENSE
Project-URL: Documentation, https://indipyclient.readthedocs.io
Project-URL: Source, https://github.com/bernie-skipole/indipyclient
